pulsequantum/__init__.py
pulsequantum/_version.py
pulsequantum/annotateshape.py
pulsequantum/app.py
pulsequantum/awg.py
pulsequantum/awgsequencing.py
pulsequantum/dftable.py
pulsequantum/elem_from_plot.py
pulsequantum/mainwindow.py
pulsequantum/pulsebuilding.py
pulsequantum/sequencebuilding.py
pulsequantum/conf/__init__.py
pulsequantum/conf/telemetry.ini
pulsequantum/initfiles/init.json
pulsequantum/initfiles/setupdefault.yaml
pulsequantum/pulselib/Dephasing.json
pulsequantum/pulselib/Pulse_Triangle.json
pulsequantum/pulselib/Spin_Funnel.json
pulsequantum/telemetry/__init__.py
pulsequantum/telemetry/telemetry_functions.py
pulsequantum-0.1.1.dist-info/LICENSE.rst
pulsequantum-0.1.1.dist-info/METADATA
pulsequantum-0.1.1.dist-info/WHEEL
pulsequantum-0.1.1.dist-info/entry_points.txt
pulsequantum-0.1.1.dist-info/top_level.txt
pulsequantum-0.1.1.dist-info/RECORD
