Metadata-Version: 2.1
Name: pulsequantum
Version: 0.1.1
Summary: Pulse building interface
Home-page: UNKNOWN
Author: Rasmus Bjerregaard Christensen
Author-email: rbcmail@gmail.com
License: UNKNOWN
Platform: UNKNOWN
Classifier: Development Status :: 2 - Pre-Alpha
Classifier: Intended Audience :: Science/Research
Classifier: Programming Language :: Python :: 3.7
Requires-Python: >=3.7
Requires-Dist: broadbean (>=0.10.0)
Requires-Dist: PyQt5
Requires-Dist: qcodes
